{
  "folder": "08NsZ90jAPygD5TT",
  "name": "Forgeron, armurier",
  "type": "carriere",
  "_id": "OAudpPIIJqdYuDi0",
  "img": "icons/svg/item-bag.svg",
  "system": {
    "description": "",
    "caracteristiques": {
      "combat": {
        "value": "1"
      },
      "connaissances": {
        "value": "1"
      },
      "discretion": {
        "value": "0"
      },
      "endurance": {
        "value": "2"
      },
      "force": {
        "value": "2"
      },
      "habilete": {
        "value": "2"
      },
      "magie": {
        "value": "0"
      },
      "mouvement": {
        "value": "0"
      },
      "perception": {
        "value": "0"
      },
      "sociabilite": {
        "value": "1"
      },
      "survie": {
        "value": "0"
      },
      "tir": {
        "value": "0"
      },
      "volonte": {
        "value": "1"
      }
    }
  },
  "effects": [],
  "flags": {},
  "_stats": {
    "systemId": "brigandyne",
    "systemVersion": "1.0.0",
    "coreVersion": "11.315",
    "createdTime": 1707858627872,
    "modifiedTime": 1707941862418,
    "lastModifiedBy": "UwlimL2UASASR0DY"
  },
  "sort": 0,
  "ownership": {
    "default": 0,
    "UwlimL2UASASR0DY": 3
  },
  "_key": "!items!OAudpPIIJqdYuDi0"
}
