{
  "folder": null,
  "name": "Bâton, gourdin",
  "type": "armeMelee",
  "img": "systems/brigandyne/assets/img/armesMelee/B%C3%A2ton%2C%20gourdin.webp",
  "system": {
    "description": "",
    "prix": 1,
    "uniteePrix": "pc",
    "degats": -2,
    "allonge": "c",
    "dissimulation": "c",
    "main": "a",
    "special": "<p>Assommant</p>"
  },
  "effects": [],
  "ownership": {
    "default": 0,
    "xnDmnudJKUg9kWx1": 3
  },
  "flags": {
    "core": {}
  },
  "_stats": {
    "systemId": "brigandyne",
    "systemVersion": "1.0.0",
    "coreVersion": "11.315",
    "createdTime": 1708030145344,
    "modifiedTime": 1708191088139,
    "lastModifiedBy": "xnDmnudJKUg9kWx1"
  },
  "_id": "Unh3zOBCaDwPwr0F",
  "sort": 200000,
  "_key": "!items!Unh3zOBCaDwPwr0F"
}
